bord/__init__.py
bord/bord.py
bord/cli.py
bord/config.py
bord-0.3.2.dist-info/entry_points.txt
bord-0.3.2.dist-info/WHEEL
bord-0.3.2.dist-info/METADATA
bord-0.3.2.dist-info/RECORD
