Metadata-Version: 2.1
Name: bord
Version: 0.3.2
Summary: 
Author: Steinn Eldjárn Sigurðarson
Author-email: steinnes@gmail.com
Requires-Python: >=3.7,<4.0
Classifier: Programming Language :: Python :: 3
Classifier: Programming Language :: Python :: 3.7
Classifier: Programming Language :: Python :: 3.8
Requires-Dist: asyncclick (>=7.0,<8.0)
Requires-Dist: pyppeteer2 (==0.2.2)
Requires-Dist: screeninfo (>=0.6.1,<0.7.0)
Requires-Dist: urllib3 (>=1.25,<2.0)
